[
  {
    "from": "Urinal",
    "to": "Neural-Bot",
    "text": "yo"
  },
  {
    "from": "Neural-Bot",
    "to": "Urinal",
    "text": "System online. Awaiting commands."
  },
  {
    "from": "rlggf",
    "to": "Neural-Bot",
    "text": "yo"
  },
  {
    "from": "rlggf",
    "to": "Neural-Bot",
    "text": "yo"
  },
  {
    "from": "rlggf",
    "to": "Neural-Bot",
    "text": "hello?"
  },
  {
    "from": "Neural-Bot",
    "to": "rlggf",
    "text": "What's the move today?"
  },
  {
    "from": "rlggf",
    "to": "Neural-Bot",
    "text": "can you answer everytime?"
  },
  {
    "from": "Neural-Bot",
    "to": "rlggf",
    "text": "Private vault accessed. Encryption active."
  },
  {
    "from": "rlggf",
    "to": "Neural-Bot",
    "text": "what'"
  }
]